stellars_jupyterlab_darcula_theme/__init__.py
stellars_jupyterlab_darcula_theme/_version.py
stellars_jupyterlab_darcula_theme-1.0.45.data/data/share/jupyter/labextensions/stellars_jupyterlab_darcula_theme/package.json
stellars_jupyterlab_darcula_theme-1.0.45.data/data/share/jupyter/labextensions/stellars_jupyterlab_darcula_theme/static/509.1cf02652ca1a06fd618b.js
stellars_jupyterlab_darcula_theme-1.0.45.data/data/share/jupyter/labextensions/stellars_jupyterlab_darcula_theme/static/remoteEntry.2b1df8f09de3d8fe542c.js
stellars_jupyterlab_darcula_theme-1.0.45.data/data/share/jupyter/labextensions/stellars_jupyterlab_darcula_theme/static/style.js
stellars_jupyterlab_darcula_theme-1.0.45.data/data/share/jupyter/labextensions/stellars_jupyterlab_darcula_theme/static/third-party-licenses.json
stellars_jupyterlab_darcula_theme-1.0.45.data/data/share/jupyter/labextensions/stellars_jupyterlab_darcula_theme/themes/stellars_jupyterlab_darcula_theme/index.css
stellars_jupyterlab_darcula_theme-1.0.45.data/data/share/jupyter/labextensions/stellars_jupyterlab_darcula_theme/themes/stellars_jupyterlab_darcula_theme/index.js
stellars_jupyterlab_darcula_theme-1.0.45.data/data/share/jupyter/labextensions/stellars_jupyterlab_darcula_theme/install.json
stellars_jupyterlab_darcula_theme-1.0.45.dist-info/METADATA
stellars_jupyterlab_darcula_theme-1.0.45.dist-info/WHEEL
stellars_jupyterlab_darcula_theme-1.0.45.dist-info/licenses/LICENSE
stellars_jupyterlab_darcula_theme-1.0.45.dist-info/RECORD
